fasta2a/__init__.py
fasta2a/applications.py
fasta2a/broker.py
fasta2a/client.py
fasta2a/schema.py
fasta2a/storage.py
fasta2a/task_manager.py
fasta2a/worker.py
fasta2a/static/docs.html
fasta2a-0.5.0.dist-info/METADATA
fasta2a-0.5.0.dist-info/WHEEL
fasta2a-0.5.0.dist-info/licenses/LICENSE
fasta2a-0.5.0.dist-info/RECORD
