Metadata-Version: 2.4
Name: fasta2a
Version: 0.5.0
Summary: Convert an AI Agent into a A2A server! ✨
Project-URL: Homepage, https://pydantic.github.io/fasta2a
Project-URL: Source, https://github.com/pydantic/fasta2a
Project-URL: Documentation, https://pydantic.github.io/fasta2a
Project-URL: Changelog, https://github.com/pydantic/fasta2a/releases
Author-email: Marcelo Trylesinski <marcelotryle@gmail.com>
License-Expression: MIT
License-File: LICENSE
Classifier: Development Status :: 4 - Beta
Classifier: Environment :: Console
Classifier: Environment :: MacOS X
Classifier: Intended Audience :: Developers
Classifier: Intended Audience :: Information Technology
Classifier: Intended Audience :: System Administrators
Classifier: License :: OSI Approved :: MIT License
Classifier: Operating System :: POSIX :: Linux
Classifier: Operating System :: Unix
Classifier: Programming Language :: Python
Classifier: Programming Language :: Python :: 3
Classifier: Programming Language :: Python :: 3 :: Only
Classifier: Programming Language :: Python :: 3.9
Classifier: Programming Language :: Python :: 3.10
Classifier: Programming Language :: Python :: 3.11
Classifier: Programming Language :: Python :: 3.12
Classifier: Programming Language :: Python :: 3.13
Classifier: Topic :: Internet
Classifier: Topic :: Software Development :: Libraries :: Python Modules
Requires-Python: >=3.9
Requires-Dist: eval-type-backport>=0.2.2; python_version <= '3.9'
Requires-Dist: opentelemetry-api>=1.28.0
Requires-Dist: pydantic>=2.10
Requires-Dist: starlette>0.29.0
Provides-Extra: logfire
Requires-Dist: logfire>=2.3; extra == 'logfire'
